{
    "name":"PresideCMS Simple Web Skeleton",
    "version":"2.0.0",
    "author":"Pixl8 Interactive",
    "slug":"preside-skeleton-basic",
    "homepage":"https://github.com/pixl8/Preside-CMS-Skeleton",
    "shortDescription":"An empty skeleton PresideCMS application with CMS features enabled",
    "createPackageDirectory": false,
    "type":"preside-skeletons",
    "location":"https://github.com/pixl8/Preside-CMS-Skeleton/archive/v2.0.0.zip",
    "repository":{
        "type":"git",
        "url":"https://github.com/pixl8/Preside-CMS-Skeleton"
    },
    "installPaths":{
        "presidecms":"preside"
    },
    "dependencies":{
        "presidecms":"stable"
    }
}
